ecifl2html/__init__.py
ecifl2html/ecifl2html.py
ecifl2html-0.0.3.dist-info/LICENSE
ecifl2html-0.0.3.dist-info/METADATA
ecifl2html-0.0.3.dist-info/WHEEL
ecifl2html-0.0.3.dist-info/top_level.txt
ecifl2html-0.0.3.dist-info/RECORD
