Metadata-Version: 2.2
Name: ecifl2html
Version: 0.0.3
Summary: A lightweight Python package for adding converting Markdown to HTML.
Home-page: https://github.com/ec-intl/ecifl2html
Author: Elizabeth Consulting International Inc.
Author-email: developers@ec-intl.com
License: Apache License 2.0
Project-URL: Homepage, https://github.com/ec-intl/ecifl2html
Project-URL: Issues, https://github.com/ec-intl/ecifl2html/issues
Classifier: Programming Language :: Python :: 3
Classifier: License :: OSI Approved :: Apache Software License
Classifier: Operating System :: OS Independent
Requires-Python: >=3.6
License-File: LICENSE
Dynamic: author
Dynamic: author-email
Dynamic: classifier
Dynamic: description
Dynamic: description-content-type
Dynamic: home-page
Dynamic: license
Dynamic: project-url
Dynamic: requires-python
Dynamic: summary
